sample/__init__.py
sample/package_data.dat
sample/simple.py
PythonTestLJC275-3.0.1.dist-info/LICENSE.txt
PythonTestLJC275-3.0.1.dist-info/METADATA
PythonTestLJC275-3.0.1.dist-info/WHEEL
PythonTestLJC275-3.0.1.dist-info/entry_points.txt
PythonTestLJC275-3.0.1.dist-info/top_level.txt
PythonTestLJC275-3.0.1.dist-info/RECORD
