Metadata-Version: 2.1
Name: PythonTestLJC275
Version: 3.0.1
Summary: A sample Python project
Author-email: LJC <632688200@gmail.com>
Maintainer-email: LJC <632688200@gmail.com>
License: Copyright (c) 2016 The Python Packaging Authority (PyPA)
Project-URL: Homepage, https://github.com/liujianchao1214/PythonTest1
Project-URL: Bug Reports, https://github.com/liujianchao1214/PythonTest1/issues
Project-URL: Funding, https://donate.pypi.org
Project-URL: Say Thanks!, https://github.com/liujianchao1214/PythonTest1
Project-URL: Source, https://github.com/liujianchao1214/PythonTest1
Keywords: sample,setuptools,development
Classifier: Development Status :: 5 - Production/Stable
Classifier: Intended Audience :: Developers
Classifier: Topic :: Software Development :: Build Tools
Classifier: License :: OSI Approved :: MIT License
Classifier: Programming Language :: Python :: 3
Classifier: Programming Language :: Python :: 3.8
Classifier: Programming Language :: Python :: 3.9
Classifier: Programming Language :: Python :: 3.10
Classifier: Programming Language :: Python :: 3.11
Classifier: Programming Language :: Python :: 3.12
Classifier: Programming Language :: Python :: 3 :: Only
Requires-Python: >=3.8
License-File: LICENSE.txt
Requires-Dist: peppercorn
Requires-Dist: node
Requires-Dist: odict
Requires-Dist: certifi
Requires-Dist: charset-normalizer
Requires-Dist: docutils
Requires-Dist: idna
Requires-Dist: importlib-metadata
Requires-Dist: keyring
Requires-Dist: mdurl
Requires-Dist: more-itertools
Requires-Dist: nh3
Requires-Dist: pip
Requires-Dist: pkginfo
Requires-Dist: plumber
Requires-Dist: pygments
Requires-Dist: requests-toolbelt
Requires-Dist: readme-renderer
Requires-Dist: requests
Requires-Dist: PythonTestLJC
Requires-Dist: PythonTestLJC1
Requires-Dist: PythonTestLJC2
Requires-Dist: PythonTestLJC3
Requires-Dist: PythonTestLJC4
Requires-Dist: PythonTestLJC5
Requires-Dist: PythonTestLJC6
Requires-Dist: PythonTestLJC7
Requires-Dist: PythonTestLJC8
Requires-Dist: PythonTestLJC9
Requires-Dist: PythonTestLJC10
Provides-Extra: dev
Requires-Dist: check-manifest ; extra == 'dev'
Provides-Extra: test
Requires-Dist: coverage ; extra == 'test'
